viper/__init__.py
viper/constants.py
viper/conversation.py
viper/mm_utils.py
viper/utils.py
viper/model/__init__.py
viper/model/apply_delta.py
viper/model/builder.py
viper/model/consolidate.py
viper/model/make_delta.py
viper/model/model_arch.py
viper/model/utils.py
viper/model/language_model/__init__.py
viper/model/language_model/jamba_model.py
viper/model/language_model/llava_falcon_mamba.py
viper/model/language_model/llava_jamba.py
viper/model/language_model/llava_llama.py
viper/model/language_model/llava_mistral.py
viper/model/language_model/llava_mpt.py
viper/model/language_model/llava_phi3.py
viper/model/language_model/llava_qwen2.py
viper/model/language_model/phi3_config.py
viper/model/language_model/phi3_model.py
viper/model/multimodal_encoder/__init__.py
viper/model/multimodal_encoder/base_encoder.py
viper/model/multimodal_encoder/builder.py
viper/model/multimodal_encoder/clip_convnext_encoder.py
viper/model/multimodal_encoder/clip_encoder.py
viper/model/multimodal_projector/__init__.py
viper/model/multimodal_projector/builder.py
viper/train/__init__.py
viper/train/llava_trainer.py
viper/train/train.py
viper/train/train_mem.py
vipervlm-0.1.0.dist-info/LICENSE
vipervlm-0.1.0.dist-info/METADATA
vipervlm-0.1.0.dist-info/WHEEL
vipervlm-0.1.0.dist-info/top_level.txt
vipervlm-0.1.0.dist-info/RECORD
