Metadata-Version: 2.1
Name: vipervlm
Version: 0.1.0
Summary: PyTorch Implementation for Viper: Open Mamba-based Vision-Language Models
Home-page: https://github.com/EvanZhuang/viper
Author: Yufan Zhuang, Pierce Chuang, Yichao Lu, Abhay Harpale, Vikas Bhardwaj, Jingbo Shang
Author-email: y5zhuang@ucsd.edu
Classifier: Programming Language :: Python :: 3
Classifier: Programming Language :: Python :: 3.7
Classifier: Programming Language :: Python :: 3.8
Classifier: Programming Language :: Python :: 3.9
Classifier: Programming Language :: Python :: 3.10
Classifier: License :: OSI Approved :: MIT License
Classifier: Operating System :: OS Independent
Classifier: Topic :: Scientific/Engineering :: Artificial Intelligence
Requires-Python: >=3.7.0
License-File: LICENSE
Requires-Dist: evaluate
Requires-Dist: gradio
Requires-Dist: huggingface-hub
Requires-Dist: nltk
Requires-Dist: numpy
Requires-Dist: packaging
Requires-Dist: pandas
Requires-Dist: Pillow
Requires-Dist: requests
Requires-Dist: scipy
Requires-Dist: timm
Requires-Dist: tokenizers
Requires-Dist: torch
Requires-Dist: tqdm
Requires-Dist: transformers
